{"nodes": [{"id": "lib_models_user_preferences_dart", "label": "user_preferences.dart", "file_type": "code", "source_file": "lib/models/user_preferences.dart", "source_location": null}, {"id": "lib_models_user_preferences_dart_userpreferences", "label": "UserPreferences", "file_type": "code", "source_file": "lib/models/user_preferences.dart", "source_location": null}, {"id": "package_hive_hive_dart", "label": "package:hive/hive.dart", "file_type": "code", "source_file": "lib/models/user_preferences.dart", "source_location": null}], "edges": [{"source": "lib_models_user_preferences_dart", "target": "lib_models_user_preferences_dart_userpreferences", "relation": "defines", "confidence": "EXTRACTED", "confidence_score": 1.0, "source_file": "lib/models/user_preferences.dart", "source_location": null, "weight": 1.0}, {"source": "lib_models_user_preferences_dart", "target": "package_hive_hive_dart", "relation": "imports", "confidence": "EXTRACTED", "confidence_score": 1.0, "source_file": "lib/models/user_preferences.dart", "source_location": null, "weight": 1.0}]}